{"box_data": [{"position": {"minX": 734.5, "minY": 494.0, "maxX": 868.5, "maxY": 831.0}, "class_id": 0, "box_caption": "target 0.238", "scores": {"class_score": 0.2384033203125}, "domain": "pixel"}, {"position": {"minX": 1048.0, "minY": 434.75, "maxX": 1280.0, "maxY": 1117.0}, "class_id": 0, "box_caption": "target 0.179", "scores": {"class_score": 0.1788330078125}, "domain": "pixel"}, {"position": {"minX": 922.5, "minY": 509.0, "maxX": 1042.0, "maxY": 860.0}, "class_id": 0, "box_caption": "target 0.170", "scores": {"class_score": 0.169921875}, "domain": "pixel"}, {"position": {"minX": 461.0, "minY": 416.5, "maxX": 677.0, "maxY": 1120.0}, "class_id": 0, "box_caption": "target 0.084", "scores": {"class_score": 0.0838623046875}, "domain": "pixel"}, {"position": {"minX": 1464.0, "minY": 851.0, "maxX": 1550.0, "maxY": 1152.0}, "class_id": 0, "box_caption": "target 0.010", "scores": {"class_score": 0.009857177734375}, "domain": "pixel"}, {"position": {"minX": 16.328125, "minY": 1012.0, "maxX": 24.484375, "maxY": 1035.0}, "class_id": 0, "box_caption": "target 0.010", "scores": {"class_score": 0.00974273681640625}, "domain": "pixel"}, {"position": {"minX": 1525.0, "minY": 877.5, "maxX": 1553.0, "maxY": 915.5}, "class_id": 0, "box_caption": "target 0.003", "scores": {"class_score": 0.0027675628662109375}, "domain": "pixel"}, {"position": {"minX": 634.0, "minY": 3.0, "maxX": 1270.0, "maxY": 391.75}, "class_id": 0, "box_caption": "target 0.002", "scores": {"class_score": 0.002208709716796875}, "domain": "pixel"}, {"position": {"minX": 1347.0, "minY": 165.5, "maxX": 1553.0, "maxY": 811.0}, "class_id": 0, "box_caption": "target 0.002", "scores": {"class_score": 0.001987457275390625}, "domain": "pixel"}, {"position": {"minX": 881.0, "minY": 13.0, "maxX": 1525.0, "maxY": 381.0}, "class_id": 0, "box_caption": "target 0.002", "scores": {"class_score": 0.0017824172973632812}, "domain": "pixel"}, {"position": {"minX": 1368.0, "minY": 431.5, "maxX": 1552.0, "maxY": 1180.0}, "class_id": 0, "box_caption": "target 0.001", "scores": {"class_score": 0.00147247314453125}, "domain": "pixel"}, {"position": {"minX": 305.25, "minY": 204.5, "maxX": 845.0, "maxY": 327.5}, "class_id": 0, "box_caption": "target 0.001", "scores": {"class_score": 0.0012998580932617188}, "domain": "pixel"}], "class_labels": {"0": "target"}}