{"box_data": [{"position": {"minX": 619.0, "minY": 347.5, "maxX": 700.0, "maxY": 582.5}, "class_id": 0, "box_caption": "target 0.149", "scores": {"class_score": 0.1488037109375}, "domain": "pixel"}, {"position": {"minX": 494.25, "minY": 336.0, "maxX": 585.0, "maxY": 558.5}, "class_id": 0, "box_caption": "target 0.134", "scores": {"class_score": 0.134033203125}, "domain": "pixel"}, {"position": {"minX": 312.5, "minY": 294.5, "maxX": 450.5, "maxY": 782.5}, "class_id": 0, "box_caption": "target 0.134", "scores": {"class_score": 0.1336669921875}, "domain": "pixel"}, {"position": {"minX": 705.0, "minY": 308.5, "maxX": 855.0, "maxY": 770.5}, "class_id": 0, "box_caption": "target 0.115", "scores": {"class_score": 0.11456298828125}, "domain": "pixel"}, {"position": {"minX": 213.875, "minY": 501.25, "maxX": 229.625, "maxY": 538.0}, "class_id": 0, "box_caption": "target 0.003", "scores": {"class_score": 0.0034160614013671875}, "domain": "pixel"}, {"position": {"minX": 17.03125, "minY": 520.0, "maxX": 37.09375, "maxY": 606.0}, "class_id": 0, "box_caption": "target 0.002", "scores": {"class_score": 0.0018033981323242188}, "domain": "pixel"}], "class_labels": {"0": "target"}}