{"box_data": [{"position": {"minX": 697.0, "minY": 308.5, "maxX": 780.0, "maxY": 722.5}, "class_id": 0, "box_caption": "target 0.011", "scores": {"class_score": 0.01094818115234375}, "domain": "pixel"}, {"position": {"minX": 899.5, "minY": 184.5, "maxX": 949.5, "maxY": 270.5}, "class_id": 0, "box_caption": "target 0.003", "scores": {"class_score": 0.0030269622802734375}, "domain": "pixel"}, {"position": {"minX": 720.0, "minY": 176.5, "maxX": 859.0, "maxY": 732.5}, "class_id": 0, "box_caption": "target 0.001", "scores": {"class_score": 0.001239776611328125}, "domain": "pixel"}], "class_labels": {"0": "target"}}