{"box_data": [{"position": {"minX": 158.75, "minY": 49.5, "maxX": 278.0, "maxY": 181.125}, "class_id": 2, "box_caption": "ok 0.948", "scores": {"class_score": 0.9482421875}, "domain": "pixel"}, {"position": {"minX": 606.5, "minY": 127.0625, "maxX": 662.5, "maxY": 273.75}, "class_id": 3, "box_caption": "palm 0.022", "scores": {"class_score": 0.0215301513671875}, "domain": "pixel"}, {"position": {"minX": 15.125, "minY": 187.75, "maxX": 99.0625, "maxY": 336.25}, "class_id": 2, "box_caption": "ok 0.006", "scores": {"class_score": 0.006084442138671875}, "domain": "pixel"}, {"position": {"minX": 155.0, "minY": 49.0625, "maxX": 280.75, "maxY": 184.75}, "class_id": 3, "box_caption": "palm 0.001", "scores": {"class_score": 0.0010366439819335938}, "domain": "pixel"}], "class_labels": {"0": "none", "1": "like", "2": "ok", "3": "palm", "4": "two_up"}}