{"box_data": [{"position": {"minX": 949.5, "minY": 408.75, "maxX": 1037.0, "maxY": 486.25}, "class_id": 0, "box_caption": "target 0.053", "scores": {"class_score": 0.053314208984375}, "domain": "pixel"}, {"position": {"minX": 955.0, "minY": 410.25, "maxX": 1037.0, "maxY": 555.0}, "class_id": 0, "box_caption": "target 0.032", "scores": {"class_score": 0.03240966796875}, "domain": "pixel"}, {"position": {"minX": 959.5, "minY": 481.0, "maxX": 1038.0, "maxY": 577.0}, "class_id": 0, "box_caption": "target 0.005", "scores": {"class_score": 0.00494384765625}, "domain": "pixel"}, {"position": {"minX": 240.125, "minY": 15.140625, "maxX": 341.5, "maxY": 67.375}, "class_id": 0, "box_caption": "target 0.002", "scores": {"class_score": 0.0020751953125}, "domain": "pixel"}, {"position": {"minX": 991.5, "minY": 16.203125, "maxX": 1040.0, "maxY": 65.1875}, "class_id": 0, "box_caption": "target 0.002", "scores": {"class_score": 0.0018825531005859375}, "domain": "pixel"}, {"position": {"minX": 249.5, "minY": 510.75, "maxX": 336.5, "maxY": 600.0}, "class_id": 0, "box_caption": "target 0.002", "scores": {"class_score": 0.0016231536865234375}, "domain": "pixel"}, {"position": {"minX": 977.0, "minY": 17.125, "maxX": 1041.0, "maxY": 172.375}, "class_id": 0, "box_caption": "target 0.001", "scores": {"class_score": 0.0011653900146484375}, "domain": "pixel"}, {"position": {"minX": 103.75, "minY": 705.0, "maxX": 301.5, "maxY": 785.0}, "class_id": 0, "box_caption": "target 0.001", "scores": {"class_score": 0.0011425018310546875}, "domain": "pixel"}, {"position": {"minX": 975.5, "minY": 18.15625, "maxX": 1036.0, "maxY": 106.875}, "class_id": 0, "box_caption": "target 0.001", "scores": {"class_score": 0.0010776519775390625}, "domain": "pixel"}, {"position": {"minX": 656.5, "minY": 390.0, "maxX": 727.5, "maxY": 686.0}, "class_id": 0, "box_caption": "target 0.001", "scores": {"class_score": 0.0010442733764648438}, "domain": "pixel"}], "class_labels": {"0": "target"}}